cbsvibpyirbis/__init__.py
cbsvibpyirbis/_common.py
cbsvibpyirbis/abstract.py
cbsvibpyirbis/alphabet.py
cbsvibpyirbis/builder.py
cbsvibpyirbis/connection.py
cbsvibpyirbis/database.py
cbsvibpyirbis/direct.py
cbsvibpyirbis/error.py
cbsvibpyirbis/export.py
cbsvibpyirbis/ini.py
cbsvibpyirbis/menus.py
cbsvibpyirbis/opt.py
cbsvibpyirbis/par.py
cbsvibpyirbis/process.py
cbsvibpyirbis/query.py
cbsvibpyirbis/records/__init__.py
cbsvibpyirbis/records/abstract.py
cbsvibpyirbis/records/field.py
cbsvibpyirbis/records/raw_record.py
cbsvibpyirbis/records/record.py
cbsvibpyirbis/records/subfield.py
cbsvibpyirbis/resource.py
cbsvibpyirbis/response.py
cbsvibpyirbis/saveable.py
cbsvibpyirbis/search.py
cbsvibpyirbis/specification.py
cbsvibpyirbis/stats.py
cbsvibpyirbis/table.py
cbsvibpyirbis/terms.py
cbsvibpyirbis/tree.py
cbsvibpyirbis/user.py
cbsvibpyirbis/version.py
cbsvibpyirbis-0.2.5.dist-info/LICENSE
cbsvibpyirbis-0.2.5.dist-info/METADATA
cbsvibpyirbis-0.2.5.dist-info/WHEEL
cbsvibpyirbis-0.2.5.dist-info/RECORD
