Metadata-Version: 2.1
Name: cbsvibpyirbis
Version: 0.2.5
Summary: Framework for client development for popular Russian library computer system IRBIS64
Home-page: https://github.com/amironov73/PythonIrbis
Keywords: IRBIS64
Author: Alexey Mironov
Author-email: amironov73@gmail.com
Requires-Python: >=3.6
Classifier: Development Status :: 3 - Alpha
Classifier: License :: OSI Approved :: MIT License
Classifier: Operating System :: OS Independent
Classifier: Programming Language :: Python
Classifier: Programming Language :: Python :: 3
Classifier: Programming Language :: Python :: 3.6
Classifier: Programming Language :: Python :: 3.7
Classifier: Programming Language :: Python :: 3.8
Classifier: Programming Language :: Python :: 3.9
Classifier: Programming Language :: Python :: 3.10
Classifier: Programming Language :: Python :: 3.11
Classifier: Programming Language :: Python :: 3.12
Project-URL: Documentation, https://pythonirbis.readthedocs.io
Project-URL: Repository, https://github.com/amironov73/PythonIrbis
